palettecleanser/__init__.py
palettecleanser/cli/__init__.py
palettecleanser/cli/main.py
palettecleanser/cli/palette.py
palettecleanser/cli/template.py
palettecleanser/cli/theme.py
palettecleanser/config.py
palettecleanser/palette.py
palettecleanser/template.py
palettecleanser/theme.py
palettecleanser-0.2.2.dist-info/entry_points.txt
palettecleanser-0.2.2.dist-info/LICENSE
palettecleanser-0.2.2.dist-info/WHEEL
palettecleanser-0.2.2.dist-info/METADATA
palettecleanser-0.2.2.dist-info/RECORD
