Metadata-Version: 2.1
Name: palettecleanser
Version: 0.2.2
Summary: 
Home-page: https://github.com/mmuldo/palette-cleanser
License: MIT
Keywords: dotfiles,configuration,customization,colorscheme,palette
Author: Matt Muldowney
Author-email: matt.muldowney@gmail.com
Requires-Python: >=3.9,<4.0
Classifier: License :: OSI Approved :: MIT License
Classifier: Programming Language :: Python :: 3
Classifier: Programming Language :: Python :: 3.9
Requires-Dist: Jinja2 (>=3.0.1,<4.0.0)
Requires-Dist: PyYAML (>=5.4.1,<6.0.0)
Requires-Dist: numpy (>=1.21.1,<2.0.0)
Requires-Dist: pywal (>=3.3.0,<4.0.0)
Requires-Dist: tabulate (>=0.8.9,<0.9.0)
Requires-Dist: typer[all] (>=0.3.2,<0.4.0)
Project-URL: Documentation, https://github.com/mmuldo/palette-cleanser/wiki
